math_mcp/__init__.py
math_mcp/__main__.py
math_mcp/basic.py
math_mcp/calculus.py
math_mcp/complex_analysis.py
math_mcp/file_utils.py
math_mcp/financial.py
math_mcp/geometry.py
math_mcp/graph_theory.py
math_mcp/math_mcp_server.py
math_mcp/matrix.py
math_mcp/mstatistics.py
math_mcp/number_theory.py
math_mcp/optimization.py
math_mcp/plotting.py
math_mcp/probability.py
math_mcp/regression.py
math_mcp/signal_processing.py
math_mcp-1.3.3.dist-info/METADATA
math_mcp-1.3.3.dist-info/WHEEL
math_mcp-1.3.3.dist-info/entry_points.txt
math_mcp-1.3.3.dist-info/licenses/LICENSE
math_mcp-1.3.3.dist-info/RECORD
